DarkMatterPy/Builtins.py
DarkMatterPy/BytecodeCaching.py
DarkMatterPy/Bytecodes.py
DarkMatterPy/CacheCleanup.py
DarkMatterPy/Constants.py
DarkMatterPy/EncryptedNexia.py
DarkMatterPy/Errors.py
DarkMatterPy/HardImportRegistry.py
DarkMatterPy/MainControl.py
DarkMatterPy/ModuleRegistry.py
DarkMatterPy/OptionParsing.py
DarkMatterPy/Options.py
DarkMatterPy/OutputDirectories.py
DarkMatterPy/PostProcessing.py
DarkMatterPy/Progress.py
DarkMatterPy/PythonFlavors.py
DarkMatterPy/PythonOperators.py
DarkMatterPy/PythonVersions.py
DarkMatterPy/Serialization.py
DarkMatterPy/SourceCodeReferences.py
DarkMatterPy/Tracing.py
DarkMatterPy/TreeXML.py
DarkMatterPy/Variables.py
DarkMatterPy/Version.py
DarkMatterPy/__init__.py
DarkMatterPy/__main__.py
DarkMatterPy/__past__.py
DarkMatterPy/build/DataComposerInterface.py
DarkMatterPy/build/SconsCaching.py
DarkMatterPy/build/SconsCompilerSettings.py
DarkMatterPy/build/SconsHacks.py
DarkMatterPy/build/SconsInterface.py
DarkMatterPy/build/SconsProgress.py
DarkMatterPy/build/SconsSpawn.py
DarkMatterPy/build/SconsUtils.py
DarkMatterPy/build/__init__.py
DarkMatterPy/build/inline_copy/appdirs/appdirs.py
DarkMatterPy/build/inline_copy/bin/scons.py
DarkMatterPy/build/inline_copy/glob2/glob2/__init__.py
DarkMatterPy/build/inline_copy/glob2/glob2/compat.py
DarkMatterPy/build/inline_copy/glob2/glob2/fnmatch.py
DarkMatterPy/build/inline_copy/glob2/glob2/impl.py
DarkMatterPy/build/inline_copy/jinja2/jinja2/__init__.py
DarkMatterPy/build/inline_copy/jinja2/jinja2/_compat.py
DarkMatterPy/build/inline_copy/jinja2/jinja2/_identifier.py
DarkMatterPy/build/inline_copy/jinja2/jinja2/bccache.py
DarkMatterPy/build/inline_copy/jinja2/jinja2/compiler.py
DarkMatterPy/build/inline_copy/jinja2/jinja2/constants.py
DarkMatterPy/build/inline_copy/jinja2/jinja2/debug.py
DarkMatterPy/build/inline_copy/jinja2/jinja2/defaults.py
DarkMatterPy/build/inline_copy/jinja2/jinja2/environment.py
DarkMatterPy/build/inline_copy/jinja2/jinja2/exceptions.py
darkmatterpy-0.1.0.dist-info/METADATA
darkmatterpy-0.1.0.dist-info/WHEEL
darkmatterpy-0.1.0.dist-info/entry_points.txt
darkmatterpy-0.1.0.dist-info/top_level.txt
darkmatterpy-0.1.0.dist-info/RECORD
